PIdecorators/__init__.py
PIdecorators/asyncio.py
PIdecorators/decorator.py
PIdecorators/tests.py
PIdecorators/util_decorators.py
PIdecorators/utils.py
pidecorators-0.3.2.dist-info/WHEEL
pidecorators-0.3.2.dist-info/METADATA
pidecorators-0.3.2.dist-info/RECORD
