Metadata-Version: 2.1
Name: pidecorators
Version: 0.3.2
Summary: A package containing some nice decorators for buzzword bonanza functions.
License: Pandora Intelligence
Author: David.Berenstein
Requires-Python: >=3.8,<4.0
Classifier: License :: Other/Proprietary License
Classifier: Programming Language :: Python :: 3
Classifier: Programming Language :: Python :: 3.8
Classifier: Programming Language :: Python :: 3.9
Requires-Dist: guppy3 (>=3.1.0,<4.0.0)
Requires-Dist: psutil (>=5.8.0,<6.0.0)
